{
  "status": "success",
  "generated_at": "2026-07-15T03:02:50.278717+09:00",
  "data": [
    {
      "time": 0,
      "speed": 0.39,
      "direction": 88.01
    },
    {
      "time": 1,
      "speed": 1.09,
      "direction": 119.42
    },
    {
      "time": 2,
      "speed": 1.52,
      "direction": 123.37
    },
    {
      "time": 3,
      "speed": 1.53,
      "direction": 121.78
    },
    {
      "time": 4,
      "speed": 1.15,
      "direction": 118.67
    },
    {
      "time": 5,
      "speed": 0.5,
      "direction": 121.97
    },
    {
      "time": 6,
      "speed": 0.33,
      "direction": 261.28
    },
    {
      "time": 7,
      "speed": 1.0,
      "direction": 275.69
    },
    {
      "time": 8,
      "speed": 1.36,
      "direction": 280.96
    },
    {
      "time": 9,
      "speed": 1.27,
      "direction": 289.28
    },
    {
      "time": 10,
      "speed": 0.79,
      "direction": 305.66
    },
    {
      "time": 11,
      "speed": 0.29,
      "direction": 25.53
    },
    {
      "time": 12,
      "speed": 0.9,
      "direction": 101.82
    },
    {
      "time": 13,
      "speed": 1.61,
      "direction": 115.18
    },
    {
      "time": 14,
      "speed": 2.0,
      "direction": 119.17
    },
    {
      "time": 15,
      "speed": 1.94,
      "direction": 118.02
    },
    {
      "time": 16,
      "speed": 1.42,
      "direction": 112.7
    },
    {
      "time": 17,
      "speed": 0.56,
      "direction": 98.99
    },
    {
      "time": 18,
      "speed": 0.51,
      "direction": 304.56
    },
    {
      "time": 19,
      "speed": 1.49,
      "direction": 291.92
    },
    {
      "time": 20,
      "speed": 2.18,
      "direction": 290.83
    },
    {
      "time": 21,
      "speed": 2.39,
      "direction": 294.17
    },
    {
      "time": 22,
      "speed": 2.09,
      "direction": 300.99
    },
    {
      "time": 23,
      "speed": 1.39,
      "direction": 311.57
    },
    {
      "time": 24,
      "speed": 0.48,
      "direction": 341.55
    },
    {
      "time": 25,
      "speed": 0.69,
      "direction": 106.25
    },
    {
      "time": 26,
      "speed": 1.46,
      "direction": 120.28
    },
    {
      "time": 27,
      "speed": 1.81,
      "direction": 121.36
    },
    {
      "time": 28,
      "speed": 1.67,
      "direction": 118.41
    },
    {
      "time": 29,
      "speed": 1.1,
      "direction": 114.61
    },
    {
      "time": 30,
      "speed": 0.27,
      "direction": 122.33
    },
    {
      "time": 31,
      "speed": 0.63,
      "direction": 275.21
    },
    {
      "time": 32,
      "speed": 1.31,
      "direction": 279.17
    },
    {
      "time": 33,
      "speed": 1.58,
      "direction": 284.0
    },
    {
      "time": 34,
      "speed": 1.36,
      "direction": 293.01
    },
    {
      "time": 35,
      "speed": 0.76,
      "direction": 311.6
    },
    {
      "time": 36,
      "speed": 0.35,
      "direction": 57.2
    },
    {
      "time": 37,
      "speed": 1.16,
      "direction": 107.93
    },
    {
      "time": 38,
      "speed": 1.91,
      "direction": 117.37
    },
    {
      "time": 39,
      "speed": 2.23,
      "direction": 119.33
    },
    {
      "time": 40,
      "speed": 2.02,
      "direction": 116.85
    },
    {
      "time": 41,
      "speed": 1.31,
      "direction": 110.54
    },
    {
      "time": 42,
      "speed": 0.29,
      "direction": 85.58
    },
    {
      "time": 43,
      "speed": 0.88,
      "direction": 295.56
    },
    {
      "time": 44,
      "speed": 1.85,
      "direction": 289.67
    },
    {
      "time": 45,
      "speed": 2.43,
      "direction": 290.28
    },
    {
      "time": 46,
      "speed": 2.47,
      "direction": 294.83
    },
    {
      "time": 47,
      "speed": 2.0,
      "direction": 302.71
    }
  ]
}